<?xml version="1.0" encoding="utf-8" ?>
<elements>
    <info>
        <name>Knowing Mind Psion</name>
        <update version="0.0.1">
            <file name="psion-knowingmind.xml" url="https://raw.githubusercontent.com/ShadowLinks/KibblesTasty-elements/refs/heads/main/Compendium/psion-knowingmind.xml" />
        </update>
    </info>
    <element name="Knowing Mind" type="Archetype" source="Kibbles' Compendium of Legends and Legacies" id="ID_KTH_COLAL_ARCHETYPE_PSION_KNOWINGMIND">
        <supports>Psionic Archetype</supports>
        <description>
            <p></p>
            <p class="indent"></p>
            <div element="ID_KTH_COLAL_ARCHETYPE_FEATURE_PSION_KNOWINGMIND_FEATURENAME" />
            <div element="ID_KTH_COLAL_ARCHETYPE_FEATURE_PSION_KNOWINGMIND_FEATURENAME" />
            <div element="ID_KTH_COLAL_ARCHETYPE_FEATURE_PSION_KNOWINGMIND_FEATURENAME" />
            <div element="ID_KTH_COLAL_ARCHETYPE_FEATURE_PSION_KNOWINGMIND_FEATURENAME" />
            <div element="ID_KTH_COLAL_ARCHETYPE_FEATURE_PSION_KNOWINGMIND_FEATURENAME" />
            <div element="ID_KTH_COLAL_ARCHETYPE_FEATURE_PSION_KNOWINGMIND_FEATURENAME" />
        </description>
        <sheet display="false">
            <description></description>
        </sheet>
        <rules>
            <grant type="Archetype Feature" id="ID_KTH_COLAL_ARCHETYPE_FEATURE_PSION_KNOWINGMIND_FEATURENAME" level="1" />
            <grant type="Archetype Feature" id="ID_KTH_COLAL_ARCHETYPE_FEATURE_PSION_KNOWINGMIND_FEATURENAME" level="1" />
            <grant type="Archetype Feature" id="ID_KTH_COLAL_ARCHETYPE_FEATURE_PSION_KNOWINGMIND_FEATURENAME" level="3" />
            <grant type="Archetype Feature" id="ID_KTH_COLAL_ARCHETYPE_FEATURE_PSION_KNOWINGMIND_FEATURENAME" level="6" />
            <grant type="Archetype Feature" id="ID_KTH_COLAL_ARCHETYPE_FEATURE_PSION_KNOWINGMIND_FEATURENAME" level="10" />
            <grant type="Archetype Feature" id="ID_KTH_COLAL_ARCHETYPE_FEATURE_PSION_KNOWINGMIND_FEATURENAME" level="14" />
        </rules>
    </element>
    <element name="Featurename" type="Archetype Feature" source="Kibbles' Compendium of Legends and Legacies" id="ID_KTH_COLAL_ARCHETYPE_FEATURE_PSION_KNOWINGMIND_FEATURENAME">
        <description>
            <p></p>
        </description>
        <sheet>
            <description></description>
        </sheet>
    </element>
    <element name="Featurename" type="Archetype Feature" source="Kibbles' Compendium of Legends and Legacies" id="ID_KTH_COLAL_ARCHETYPE_FEATURE_PSION_KNOWINGMIND_FEATURENAME">
        <description>
            <p></p>
        </description>
        <sheet>
            <description></description>
        </sheet>
    </element>
    <element name="Featurename" type="Archetype Feature" source="Kibbles' Compendium of Legends and Legacies" id="ID_KTH_COLAL_ARCHETYPE_FEATURE_PSION_KNOWINGMIND_FEATURENAME">
        <description>
            <p></p>
        </description>
        <sheet>
            <description></description>
        </sheet>
    </element>
    <element name="Featurename" type="Archetype Feature" source="Kibbles' Compendium of Legends and Legacies" id="ID_KTH_COLAL_ARCHETYPE_FEATURE_PSION_KNOWINGMIND_FEATURENAME">
        <description>
            <p></p>
        </description>
        <sheet>
            <description></description>
        </sheet>
    </element>
    <element name="Featurename" type="Archetype Feature" source="Kibbles' Compendium of Legends and Legacies" id="ID_KTH_COLAL_ARCHETYPE_FEATURE_PSION_KNOWINGMIND_FEATURENAME">
        <description>
            <p></p>
        </description>
        <sheet>
            <description></description>
        </sheet>
    </element>
    <element name="Featurename" type="Archetype Feature" source="Kibbles' Compendium of Legends and Legacies" id="ID_KTH_COLAL_ARCHETYPE_FEATURE_PSION_KNOWINGMIND_FEATURENAME">
        <description>
            <p></p>
        </description>
        <sheet>
            <description></description>
        </sheet>
    </element>
</elements>